windfetch/__init__.py
windfetch/loader.py
windfetch/windfetch.py
windfetch-0.0.2.dist-info/licenses/LICENSE
windfetch-0.0.2.dist-info/METADATA
windfetch-0.0.2.dist-info/WHEEL
windfetch-0.0.2.dist-info/entry_points.txt
windfetch-0.0.2.dist-info/top_level.txt
windfetch-0.0.2.dist-info/RECORD
