Metadata-Version: 2.4
Name: windfetch
Version: 0.0.2
Summary: An elegant Python system information tool, inspired by `neofetch`
Author-email: "星灿长风v(StarWindv)" <starwindv.stv@gmail.com>
License-Expression: MIT
Project-URL: Homepage, https://github.com/StarWindv/pyfetch
Classifier: Programming Language :: Python :: 3
Requires-Python: >=3.10
License-File: LICENSE
Requires-Dist: requests
Requires-Dist: stv_utils>=0.0.8
Requires-Dist: psutil
Dynamic: license-file
